aimon_llamaindex/__init__.py
aimon_llamaindex/main.py
aimon_llamaindex-0.4.1.dist-info/METADATA
aimon_llamaindex-0.4.1.dist-info/WHEEL
aimon_llamaindex-0.4.1.dist-info/top_level.txt
aimon_llamaindex-0.4.1.dist-info/RECORD
