Metadata-Version: 2.1
Name: aimon-llamaindex
Version: 0.4.1
Summary: aimon-llamaindex package
Author: Devvrat Bhardwaj
Requires-Dist: aimon
Requires-Dist: llama-index
Requires-Dist: llama-index-vector-stores-milvus
